vndb_api_wrapper/vndb_api.py
vndb_api_wrapper/vndb_info.py
vndb_api_wrapper/exceptions/vndb_error.py
vndb_api_wrapper/utils/utils.py
vndb_api_wrapper-1.0.0a0.dist-info/LICENSE
vndb_api_wrapper-1.0.0a0.dist-info/METADATA
vndb_api_wrapper-1.0.0a0.dist-info/WHEEL
vndb_api_wrapper-1.0.0a0.dist-info/top_level.txt
vndb_api_wrapper-1.0.0a0.dist-info/RECORD
