Metadata-Version: 2.1
Name: vndb-api-wrapper
Version: 1.0.0a0
Summary: A wrapper for the VNDB API
Home-page: https://github.com/PoeticViper/VNDB-Python-API-Wrapper
Author: PoeticViper
Author-email: PoeticViper@users.noreply.github.com
License: GPLv3
Platform: UNKNOWN
